riscv/regfile/riscv_regfile.v
//-----------------------------------------------------------------
//                         RISC-V Core
//                            V1.0.1
//                     Ultra-Embedded.com
//                     Copyright 2014-2019
//
//                   admin@ultra-embedded.com
//
//                       License: BSD
//-----------------------------------------------------------------
module riscv_regfile
(
    // Inputs
     input           clk_i
    ,input           rst_i
    ,input  [  4:0]  rd0_i
    ,input  [ 31:0]  rd0_value_i
    ,input  [  4:0]  ra0_i
    ,input  [  4:0]  rb0_i

    // Outputs
    ,output [ 31:0]  ra0_value_o
    ,output [ 31:0]  rb0_value_o
);

//-----------------------------------------------------------------
// Register file declaration
//-----------------------------------------------------------------
reg [31:0] reg_r1_q;
reg [31:0] reg_r2_q;
reg [31:0] reg_r3_q;
reg [31:0] reg_r4_q;
reg [31:0] reg_r5_q;
reg [31:0] reg_r6_q;
reg [31:0] reg_r7_q;
reg [31:0] reg_r8_q;
reg [31:0] reg_r9_q;
reg [31:0] reg_r10_q;
reg [31:0] reg_r11_q;
reg [31:0] reg_r12_q;
reg [31:0] reg_r13_q;
reg [31:0] reg_r14_q;
reg [31:0] reg_r15_q;
reg [31:0] reg_r16_q;
reg [31:0] reg_r17_q;
reg [31:0] reg_r18_q;
reg [31:0] reg_r19_q;
reg [31:0] reg_r20_q;
reg [31:0] reg_r21_q;
reg [31:0] reg_r22_q;
reg [31:0] reg_r23_q;
reg [31:0] reg_r24_q;
reg [31:0] reg_r25_q;
reg [31:0] reg_r26_q;
reg [31:0] reg_r27_q;
reg [31:0] reg_r28_q;
reg [31:0] reg_r29_q;
reg [31:0] reg_r30_q;
reg [31:0] reg_r31_q;

// Simulation friendly names
wire [31:0] x0_zero_w = 32'b0;
wire [31:0] x1_ra_w   = reg_r1_q;
wire [31:0] x2_sp_w   = reg_r2_q;
wire [31:0] x3_gp_w   = reg_r3_q;
wire [31:0] x4_tp_w   = reg_r4_q;
wire [31:0] x5_t0_w   = reg_r5_q;
wire [31:0] x6_t1_w   = reg_r6_q;
wire [31:0] x7_t2_w   = reg_r7_q;
wire [31:0] x8_s0_w   = reg_r8_q;
wire [31:0] x9_s1_w   = reg_r9_q;
wire [31:0] x10_a0_w  = reg_r10_q;
wire [31:0] x11_a1_w  = reg_r11_q;
wire [31:0] x12_a2_w  = reg_r12_q;
wire [31:0] x13_a3_w  = reg_r13_q;
wire [31:0] x14_a4_w  = reg_r14_q;
wire [31:0] x15_a5_w  = reg_r15_q;
wire [31:0] x16_a6_w  = reg_r16_q;
wire [31:0] x17_a7_w  = reg_r17_q;
wire [31:0] x18_s2_w  = reg_r18_q;
wire [31:0] x19_s3_w  = reg_r19_q;
wire [31:0] x20_s4_w  = reg_r20_q;
wire [31:0] x21_s5_w  = reg_r21_q;
wire [31:0] x22_s6_w  = reg_r22_q;
wire [31:0] x23_s7_w  = reg_r23_q;
wire [31:0] x24_s8_w  = reg_r24_q;
wire [31:0] x25_s9_w  = reg_r25_q;
wire [31:0] x26_s10_w = reg_r26_q;
wire [31:0] x27_s11_w = reg_r27_q;
wire [31:0] x28_t3_w  = reg_r28_q;
wire [31:0] x29_t4_w  = reg_r29_q;
wire [31:0] x30_t5_w  = reg_r30_q;
wire [31:0] x31_t6_w  = reg_r31_q;

//-----------------------------------------------------------------
// Synchronous register write back
//-----------------------------------------------------------------
always @ (posedge clk_i) begin
    if (rst_i) begin
        reg_r1_q       <= 32'h00000000;
        reg_r2_q       <= 32'h00000000;
        reg_r3_q       <= 32'h00000000;
        reg_r4_q       <= 32'h00000000;
        reg_r5_q       <= 32'h00000000;
        reg_r6_q       <= 32'h00000000;
        reg_r7_q       <= 32'h00000000;
        reg_r8_q       <= 32'h00000000;
        reg_r9_q       <= 32'h00000000;
        reg_r10_q      <= 32'h00000000;
        reg_r11_q      <= 32'h00000000;
        reg_r12_q      <= 32'h00000000;
        reg_r13_q      <= 32'h00000000;
        reg_r14_q      <= 32'h00000000;
        reg_r15_q      <= 32'h00000000;
        reg_r16_q      <= 32'h00000000;
        reg_r17_q      <= 32'h00000000;
        reg_r18_q      <= 32'h00000000;
        reg_r19_q      <= 32'h00000000;
        reg_r20_q      <= 32'h00000000;
        reg_r21_q      <= 32'h00000000;
        reg_r22_q      <= 32'h00000000;
        reg_r23_q      <= 32'h00000000;
        reg_r24_q      <= 32'h00000000;
        reg_r25_q      <= 32'h00000000;
        reg_r26_q      <= 32'h00000000;
        reg_r27_q      <= 32'h00000000;
        reg_r28_q      <= 32'h00000000;
        reg_r29_q      <= 32'h00000000;
        reg_r30_q      <= 32'h00000000;
        reg_r31_q      <= 32'h00000000;
    end
    else begin
        // Write to register file (x0 is hardwired to 0)
        case (rd0_i)
            5'd1:  reg_r1_q  <= rd0_value_i;
            5'd2:  reg_r2_q  <= rd0_value_i;
            5'd3:  reg_r3_q  <= rd0_value_i;
            5'd4:  reg_r4_q  <= rd0_value_i;
            5'd5:  reg_r5_q  <= rd0_value_i;
            5'd6:  reg_r6_q  <= rd0_value_i;
            5'd7:  reg_r7_q  <= rd0_value_i;
            5'd8:  reg_r8_q  <= rd0_value_i;
            5'd9:  reg_r9_q  <= rd0_value_i;
            5'd10: reg_r10_q <= rd0_value_i;
            5'd11: reg_r11_q <= rd0_value_i;
            5'd12: reg_r12_q <= rd0_value_i;
            5'd13: reg_r13_q <= rd0_value_i;
            5'd14: reg_r14_q <= rd0_value_i;
            5'd15: reg_r15_q <= rd0_value_i;
            5'd16: reg_r16_q <= rd0_value_i;
            5'd17: reg_r17_q <= rd0_value_i;
            5'd18: reg_r18_q <= rd0_value_i;
            5'd19: reg_r19_q <= rd0_value_i;
            5'd20: reg_r20_q <= rd0_value_i;
            5'd21: reg_r21_q <= rd0_value_i;
            5'd22: reg_r22_q <= rd0_value_i;
            5'd23: reg_r23_q <= rd0_value_i;
            5'd24: reg_r24_q <= rd0_value_i;
            5'd25: reg_r25_q <= rd0_value_i;
            5'd26: reg_r26_q <= rd0_value_i;
            5'd27: reg_r27_q <= rd0_value_i;
            5'd28: reg_r28_q <= rd0_value_i;
            5'd29: reg_r29_q <= rd0_value_i;
            5'd30: reg_r30_q <= rd0_value_i;
            5'd31: reg_r31_q <= rd0_value_i;
            default: ; // x0 is read-only zero
        endcase
    end
end

//-----------------------------------------------------------------
// Asynchronous read port A
//-----------------------------------------------------------------
reg [31:0] ra0_value_r;
always @ (*) begin
    case (ra0_i)
        5'd1:  ra0_value_r = reg_r1_q;
        5'd2:  ra0_value_r = reg_r2_q;
        5'd3:  ra0_value_r = reg_r3_q;
        5'd4:  ra0_value_r = reg_r4_q;
        5'd5:  ra0_value_r = reg_r5_q;
        5'd6:  ra0_value_r = reg_r6_q;
        5'd7:  ra0_value_r = reg_r7_q;
        5'd8:  ra0_value_r = reg_r8_q;
        5'd9:  ra0_value_r = reg_r9_q;
        5'd10: ra0_value_r = reg_r10_q;
        5'd11: ra0_value_r = reg_r11_q;
        5'd12: ra0_value_r = reg_r12_q;
        5'd13: ra0_value_r = reg_r13_q;
        5'd14: ra0_value_r = reg_r14_q;
        5'd15: ra0_value_r = reg_r15_q;
        5'd16: ra0_value_r = reg_r16_q;
        5'd17: ra0_value_r = reg_r17_q;
        5'd18: ra0_value_r = reg_r18_q;
        5'd19: ra0_value_r = reg_r19_q;
        5'd20: ra0_value_r = reg_r20_q;
        5'd21: ra0_value_r = reg_r21_q;
        5'd22: ra0_value_r = reg_r22_q;
        5'd23: ra0_value_r = reg_r23_q;
        5'd24: ra0_value_r = reg_r24_q;
        5'd25: ra0_value_r = reg_r25_q;
        5'd26: ra0_value_r = reg_r26_q;
        5'd27: ra0_value_r = reg_r27_q;
        5'd28: ra0_value_r = reg_r28_q;
        5'd29: ra0_value_r = reg_r29_q;
        5'd30: ra0_value_r = reg_r30_q;
        5'd31: ra0_value_r = reg_r31_q;
        default: ra0_value_r = 32'h00000000; // x0 always returns 0
    endcase
end

//-----------------------------------------------------------------
// Asynchronous read port B
//-----------------------------------------------------------------
reg [31:0] rb0_value_r;
always @ (*) begin
    case (rb0_i)
        5'd1:  rb0_value_r = reg_r1_q;
        5'd2:  rb0_value_r = reg_r2_q;
        5'd3:  rb0_value_r = reg_r3_q;
        5'd4:  rb0_value_r = reg_r4_q;
        5'd5:  rb0_value_r = reg_r5_q;
        5'd6:  rb0_value_r = reg_r6_q;
        5'd7:  rb0_value_r = reg_r7_q;
        5'd8:  rb0_value_r = reg_r8_q;
        5'd9:  rb0_value_r = reg_r9_q;
        5'd10: rb0_value_r = reg_r10_q;
        5'd11: rb0_value_r = reg_r11_q;
        5'd12: rb0_value_r = reg_r12_q;
        5'd13: rb0_value_r = reg_r13_q;
        5'd14: rb0_value_r = reg_r14_q;
        5'd15: rb0_value_r = reg_r15_q;
        5'd16: rb0_value_r = reg_r16_q;
        5'd17: rb0_value_r = reg_r17_q;
        5'd18: rb0_value_r = reg_r18_q;
        5'd19: rb0_value_r = reg_r19_q;
        5'd20: rb0_value_r = reg_r20_q;
        5'd21: rb0_value_r = reg_r21_q;
        5'd22: rb0_value_r = reg_r22_q;
        5'd23: rb0_value_r = reg_r23_q;
        5'd24: rb0_value_r = reg_r24_q;
        5'd25: rb0_value_r = reg_r25_q;
        5'd26: rb0_value_r = reg_r26_q;
        5'd27: rb0_value_r = reg_r27_q;
        5'd28: rb0_value_r = reg_r28_q;
        5'd29: rb0_value_r = reg_r29_q;
        5'd30: rb0_value_r = reg_r30_q;
        5'd31: rb0_value_r = reg_r31_q;
        default: rb0_value_r = 32'h00000000; // x0 always returns 0
    endcase
end

assign ra0_value_o = ra0_value_r;
assign rb0_value_o = rb0_value_r;

`ifdef verilator
//-------------------------------------------------------------
// get_register: Read register file
//-------------------------------------------------------------
function [31:0] get_register; /*verilator public*/
    input [4:0] r;
begin
    case (r)
        5'd1:  get_register = reg_r1_q;
        5'd2:  get_register = reg_r2_q;
        5'd3:  get_register = reg_r3_q;
        5'd4:  get_register = reg_r4_q;
        5'd5:  get_register = reg_r5_q;
        5'd6:  get_register = reg_r6_q;
        5'd7:  get_register = reg_r7_q;
        5'd8:  get_register = reg_r8_q;
        5'd9:  get_register = reg_r9_q;
        5'd10: get_register = reg_r10_q;
        5'd11: get_register = reg_r11_q;
        5'd12: get_register = reg_r12_q;
        5'd13: get_register = reg_r13_q;
        5'd14: get_register = reg_r14_q;
        5'd15: get_register = reg_r15_q;
        5'd16: get_register = reg_r16_q;
        5'd17: get_register = reg_r17_q;
        5'd18: get_register = reg_r18_q;
        5'd19: get_register = reg_r19_q;
        5'd20: get_register = reg_r20_q;
        5'd21: get_register = reg_r21_q;
        5'd22: get_register = reg_r22_q;
        5'd23: get_register = reg_r23_q;
        5'd24: get_register = reg_r24_q;
        5'd25: get_register = reg_r25_q;
        5'd26: get_register = reg_r26_q;
        5'd27: get_register = reg_r27_q;
        5'd28: get_register = reg_r28_q;
        5'd29: get_register = reg_r29_q;
        5'd30: get_register = reg_r30_q;
        5'd31: get_register = reg_r31_q;
        default: get_register = 32'h00000000;
    endcase
end
endfunction
`endif

endmodule

riscv/regfile/tb_riscv_regfile.v
`timescale 1ns/1ps
`include "riscv_regfile.v"
module riscv_regfile_tb;

//-----------------------------------------------------------------
// Tín hiệu testbench
//-----------------------------------------------------------------
reg         clk_i;
reg         rst_i;
reg  [4:0]  rd0_i;
reg  [31:0] rd0_value_i;
reg  [4:0]  ra0_i;
reg  [4:0]  rb0_i;
wire [31:0] ra0_value_o;
wire [31:0] rb0_value_o;
   integer i;
//-----------------------------------------------------------------
// DUT: Device Under Test
//-----------------------------------------------------------------
riscv_regfile uut (
    .clk_i(clk_i),
    .rst_i(rst_i),
    .rd0_i(rd0_i),
    .rd0_value_i(rd0_value_i),
    .ra0_i(ra0_i),
    .rb0_i(rb0_i),
    .ra0_value_o(ra0_value_o),
    .rb0_value_o(rb0_value_o)
);

//-----------------------------------------------------------------
// Clock generator: 10ns period (100MHz)
//-----------------------------------------------------------------
always #5 clk_i = ~clk_i;

//-----------------------------------------------------------------
// Task: write register
//-----------------------------------------------------------------
task write_reg(input [4:0] reg_id, input [31:0] value);
begin
    @(negedge clk_i);
    rd0_i       = reg_id;
    rd0_value_i = value;
    @(negedge clk_i);
    rd0_i       = 0;   // stop writing
end
endtask

//-----------------------------------------------------------------
// Task: read two registers
//-----------------------------------------------------------------
task read_regs(input [4:0] ra, input [4:0] rb);
begin
    ra0_i = ra;
    rb0_i = rb;
    #1; // wait small time for async read
    $display("  Read ra=%0d -> %h | rb=%0d -> %h", ra, ra0_value_o, rb, rb0_value_o);
end
endtask

initial begin
    $dumpfile("tb_riscv_regfile.vcd");
    $dumpvars(0, riscv_regfile_tb);
end

//-----------------------------------------------------------------
// Test sequence
//-----------------------------------------------------------------
initial begin
    $display("========================================");
    $display("     TEST RISC-V REGISTER FILE");
    $display("========================================");

    // Init
    clk_i = 0;
    rst_i = 1;
    rd0_i = 0;
    rd0_value_i = 0;
    ra0_i = 0;
    rb0_i = 0;

    // Reset phase
    repeat (3) @(posedge clk_i);
    rst_i = 0;
    $display("Reset released");

    //-------------------------------------------------------------
    // 1. Check that x0 always 0
    //-------------------------------------------------------------
    write_reg(5'd0, 32'hDEADBEEF);
    read_regs(5'd0, 5'd0);
    if (ra0_value_o !== 32'h00000000)
        $display("ERROR: x0 != 0 (value=%h)", ra0_value_o);
    else
        $display("PASS: x0 is hardwired to zero");

    //-------------------------------------------------------------
    // 2. Write and read registers
    //-------------------------------------------------------------
    write_reg(5'd1, 32'h11111111);
    write_reg(5'd2, 32'h22222222);
    write_reg(5'd3, 32'h33333333);
    write_reg(5'd10, 32'hAAAA5555);

    // Read back
    read_regs(5'd1, 5'd2);
    read_regs(5'd3, 5'd10);

    //-------------------------------------------------------------
    // 3. Overwrite a register and check update
    //-------------------------------------------------------------
    write_reg(5'd1, 32'h12345678);
    read_regs(5'd1, 5'd10);

    //-------------------------------------------------------------
    // 4. Random test
    //-------------------------------------------------------------
    $display("Random test:");
 
    for (i = 4; i < 8; i = i + 1) begin
        write_reg(i, i * 32'h10);
    end
    read_regs(5'd4, 5'd7);

    //-------------------------------------------------------------
    // 5. End simulation
    //-------------------------------------------------------------
    $display("All tests finished.");
    #20;
    $finish;
end

endmodule

riscv/regfile/tb_riscv_regfile.vcd
$date
	Mon Oct 27 10:00:44 2025
$end
$version
	Icarus Verilog
$end
$timescale
	1ps
$end
$scope module riscv_regfile_tb $end
$var wire 32 ! rb0_value_o [31:0] $end
$var wire 32 " ra0_value_o [31:0] $end
$var reg 1 # clk_i $end
$var reg 5 $ ra0_i [4:0] $end
$var reg 5 % rb0_i [4:0] $end
$var reg 5 & rd0_i [4:0] $end
$var reg 32 ' rd0_value_i [31:0] $end
$var reg 1 ( rst_i $end
$var integer 32 ) i [31:0] $end
$scope module uut $end
$var wire 1 # clk_i $end
$var wire 5 * ra0_i [4:0] $end
$var wire 32 + ra0_value_o [31:0] $end
$var wire 5 , rb0_i [4:0] $end
$var wire 32 - rb0_value_o [31:0] $end
$var wire 5 . rd0_i [4:0] $end
$var wire 32 / rd0_value_i [31:0] $end
$var wire 1 ( rst_i $end
$var wire 32 0 x0_zero_w [31:0] $end
$var wire 32 1 x10_a0_w [31:0] $end
$var wire 32 2 x11_a1_w [31:0] $end
$var wire 32 3 x12_a2_w [31:0] $end
$var wire 32 4 x13_a3_w [31:0] $end
$var wire 32 5 x14_a4_w [31:0] $end
$var wire 32 6 x15_a5_w [31:0] $end
$var wire 32 7 x16_a6_w [31:0] $end
$var wire 32 8 x17_a7_w [31:0] $end
$var wire 32 9 x18_s2_w [31:0] $end
$var wire 32 : x19_s3_w [31:0] $end
$var wire 32 ; x1_ra_w [31:0] $end
$var wire 32 < x20_s4_w [31:0] $end
$var wire 32 = x21_s5_w [31:0] $end
$var wire 32 > x22_s6_w [31:0] $end
$var wire 32 ? x23_s7_w [31:0] $end
$var wire 32 @ x24_s8_w [31:0] $end
$var wire 32 A x25_s9_w [31:0] $end
$var wire 32 B x26_s10_w [31:0] $end
$var wire 32 C x27_s11_w [31:0] $end
$var wire 32 D x28_t3_w [31:0] $end
$var wire 32 E x29_t4_w [31:0] $end
$var wire 32 F x2_sp_w [31:0] $end
$var wire 32 G x30_t5_w [31:0] $end
$var wire 32 H x31_t6_w [31:0] $end
$var wire 32 I x3_gp_w [31:0] $end
$var wire 32 J x4_tp_w [31:0] $end
$var wire 32 K x5_t0_w [31:0] $end
$var wire 32 L x6_t1_w [31:0] $end
$var wire 32 M x7_t2_w [31:0] $end
$var wire 32 N x8_s0_w [31:0] $end
$var wire 32 O x9_s1_w [31:0] $end
$var reg 32 P ra0_value_r [31:0] $end
$var reg 32 Q rb0_value_r [31:0] $end
$var reg 32 R reg_r10_q [31:0] $end
$var reg 32 S reg_r11_q [31:0] $end
$var reg 32 T reg_r12_q [31:0] $end
$var reg 32 U reg_r13_q [31:0] $end
$var reg 32 V reg_r14_q [31:0] $end
$var reg 32 W reg_r15_q [31:0] $end
$var reg 32 X reg_r16_q [31:0] $end
$var reg 32 Y reg_r17_q [31:0] $end
$var reg 32 Z reg_r18_q [31:0] $end
$var reg 32 [ reg_r19_q [31:0] $end
$var reg 32 \ reg_r1_q [31:0] $end
$var reg 32 ] reg_r20_q [31:0] $end
$var reg 32 ^ reg_r21_q [31:0] $end
$var reg 32 _ reg_r22_q [31:0] $end
$var reg 32 ` reg_r23_q [31:0] $end
$var reg 32 a reg_r24_q [31:0] $end
$var reg 32 b reg_r25_q [31:0] $end
$var reg 32 c reg_r26_q [31:0] $end
$var reg 32 d reg_r27_q [31:0] $end
$var reg 32 e reg_r28_q [31:0] $end
$var reg 32 f reg_r29_q [31:0] $end
$var reg 32 g reg_r2_q [31:0] $end
$var reg 32 h reg_r30_q [31:0] $end
$var reg 32 i reg_r31_q [31:0] $end
$var reg 32 j reg_r3_q [31:0] $end
$var reg 32 k reg_r4_q [31:0] $end
$var reg 32 l reg_r5_q [31:0] $end
$var reg 32 m reg_r6_q [31:0] $end
$var reg 32 n reg_r7_q [31:0] $end
$var reg 32 o reg_r8_q [31:0] $end
$var reg 32 p reg_r9_q [31:0] $end
$upscope $end
$scope task read_regs $end
$var reg 5 q ra [4:0] $end
$var reg 5 r rb [4:0] $end
$upscope $end
$scope task write_reg $end
$var reg 5 s reg_id [4:0] $end
$var reg 32 t value [31:0] $end
$upscope $end
$upscope $end
$enddefinitions $end
$comment Show the parameter values. $end
$dumpall
$end
#0
$dumpvars
bx t
bx s
bx r
bx q
bx p
bx o
bx n
bx m
bx l
bx k
bx j
bx i
bx h
bx g
bx f
bx e
bx d
bx c
bx b
bx a
bx `
bx _
bx ^
bx ]
bx \
bx [
bx Z
bx Y
bx X
bx W
bx V
bx U
bx T
bx S
bx R
b0 Q
b0 P
bx O
bx N
bx M
bx L
bx K
bx J
bx I
bx H
bx G
bx F
bx E
bx D
bx C
bx B
bx A
bx @
bx ?
bx >
bx =
bx <
bx ;
bx :
bx 9
bx 8
bx 7
bx 6
bx 5
bx 4
bx 3
bx 2
bx 1
b0 0
b0 /
b0 .
b0 -
b0 ,
b0 +
b0 *
bx )
1(
b0 '
b0 &
b0 %
b0 $
0#
b0 "
b0 !
$end
#5000
b0 H
b0 i
b0 G
b0 h
b0 E
b0 f
b0 D
b0 e
b0 C
b0 d
b0 B
b0 c
b0 A
b0 b
b0 @
b0 a
b0 ?
b0 `
b0 >
b0 _
b0 =
b0 ^
b0 <
b0 ]
b0 :
b0 [
b0 9
b0 Z
b0 8
b0 Y
b0 7
b0 X
b0 6
b0 W
b0 5
b0 V
b0 4
b0 U
b0 3
b0 T
b0 2
b0 S
b0 1
b0 R
b0 O
b0 p
b0 N
b0 o
b0 M
b0 n
b0 L
b0 m
b0 K
b0 l
b0 J
b0 k
b0 I
b0 j
b0 F
b0 g
b0 ;
b0 \
1#
#10000
0#
#15000
1#
#20000
0#
#25000
b11011110101011011011111011101111 t
b0 s
0(
1#
#30000
b11011110101011011011111011101111 '
b11011110101011011011111011101111 /
0#
#35000
1#
#40000
b0 r
b0 q
0#
#41000
b10001000100010001000100010001 t
b1 s
#45000
1#
#50000
b10001000100010001000100010001 '
b10001000100010001000100010001 /
b1 &
b1 .
0#
#55000
b10001000100010001000100010001 ;
b10001000100010001000100010001 \
1#
#60000
b100010001000100010001000100010 t
b10 s
b0 &
b0 .
0#
#65000
1#
#70000
b100010001000100010001000100010 '
b100010001000100010001000100010 /
b10 &
b10 .
0#
#75000
b100010001000100010001000100010 F
b100010001000100010001000100010 g
1#
#80000
b110011001100110011001100110011 t
b11 s
b0 &
b0 .
0#
#85000
1#
#90000
b110011001100110011001100110011 '
b110011001100110011001100110011 /
b11 &
b11 .
0#
#95000
b110011001100110011001100110011 I
b110011001100110011001100110011 j
1#
#100000
b10101010101010100101010101010101 t
b1010 s
b0 &
b0 .
0#
#105000
1#
#110000
b10101010101010100101010101010101 '
b10101010101010100101010101010101 /
b1010 &
b1010 .
0#
#115000
b10101010101010100101010101010101 1
b10101010101010100101010101010101 R
1#
#120000
b100010001000100010001000100010 !
b100010001000100010001000100010 -
b100010001000100010001000100010 Q
b10001000100010001000100010001 "
b10001000100010001000100010001 +
b10001000100010001000100010001 P
b10 %
b10 ,
b1 $
b1 *
b10 r
b1 q
b0 &
b0 .
0#
#121000
b10101010101010100101010101010101 !
b10101010101010100101010101010101 -
b10101010101010100101010101010101 Q
b110011001100110011001100110011 "
b110011001100110011001100110011 +
b110011001100110011001100110011 P
b1010 %
b1010 ,
b11 $
b11 *
b1010 r
b11 q
#122000
b10010001101000101011001111000 t
b1 s
#125000
1#
#130000
b10010001101000101011001111000 '
b10010001101000101011001111000 /
b1 &
b1 .
0#
#135000
b10010001101000101011001111000 ;
b10010001101000101011001111000 \
1#
#140000
b10010001101000101011001111000 "
b10010001101000101011001111000 +
b10010001101000101011001111000 P
b1 $
b1 *
b1 q
b0 &
b0 .
0#
#141000
b1000000 t
b100 s
b100 )
#145000
1#
#150000
b1000000 '
b1000000 /
b100 &
b100 .
0#
#155000
b1000000 J
b1000000 k
1#
#160000
b1010000 t
b101 s
b101 )
b0 &
b0 .
0#
#165000
1#
#170000
b1010000 '
b1010000 /
b101 &
b101 .
0#
#175000
b1010000 K
b1010000 l
1#
#180000
b1100000 t
b110 s
b110 )
b0 &
b0 .
0#
#185000
1#
#190000
b1100000 '
b1100000 /
b110 &
b110 .
0#
#195000
b1100000 L
b1100000 m
1#
#200000
b1110000 t
b111 s
b111 )
b0 &
b0 .
0#
#205000
1#
#210000
b1110000 '
b1110000 /
b111 &
b111 .
0#
#215000
b1110000 M
b1110000 n
1#
#220000
b1110000 !
b1110000 -
b1110000 Q
b1000000 "
b1000000 +
b1000000 P
b111 %
b111 ,
b100 $
b100 *
b111 r
b100 q
b1000 )
b0 &
b0 .
0#
